Workbook

Sheet Page1
A1: MERCHANT | B1: INVOICE
A2: JAIKVIN GLOBAL | F2: Invoice No. | G2: JG/26-27/6002 DT 04.05.2026 | K2: Exporter's Ref.
F3: Date: | K3: IEC AVIPS4808H
A4: Merchant Exporters | F4: Buyers Order No: | H4: JG/26-P/09 DT 27.04.2026
A5: A-101, Rajshree Royale, Navroji Lane, Ghatkopar (W),
A6: MUMBAI-400 086. Maharashtra (State Code : 27) | F6: Other Reference(s):
A7: Tel: 9987122600 E-Mail: aalok.shah@jaikvinglobal.com
A8: On Account & Risks of: | F8: IRN No | G8: 5049ef43c7126a4c35bf29795ce49390de0338
A9: Messrs Corecomp Pty Ltd., | G9: c2897a4b4929c186580cfacad7
A10: T/A G.D.Watermark | F10: Ack No | G10: 122632432448548
A11: 13, Tesla Link,
A12: Wangara WA 6065 (Australia) | F12: Ack Dt | G12: 04-05-2026 3:51:00 PM
A13: Invoice of: | B13: PLASTIC (PP) EXTRUDED PIPES, PLASTIC (PP) | F13: Country of Origin | I13: Country of Final Destination
B14: & (PA) MOULDED FITTINGS AND CORRUGATED | F14: INDIA | I14: AUSTRALIA
B15: BOXES | F15: BL. NO. | G15: SFPM2605165498 DT. 19.05.2026
A16: Pre-Carraige by: | C16: Place of Receipt by Pre-Carraige | F16: Shipped Per | G16: CAPE SYROS VOYAGE 092E
F17: S/B No: | G17: 2945305 DT. 04.05.2026
A18: Shipped per: | C18: Port of Loading: | F18: Terms of Delivery: | H18: FOB MUMBAI
A19: =G16 -> CAPE SYROS VOYAGE 092E | C19: NHAVA SHEVA-MUMBAI (INDIA) | F19: Terms of Payment: | H19: D.P.SIGHT DRAFT
A20: Port of Discharge: | C20: Port of destination | F20: Through: | H20: HDFC BANK LTD, GHATKOPAR (E) BRANCH
A21: FREMANTLE | C21: FREMANTLE | H21: GHATKOPAR (E), MUMBAI 400 077 (INDIA)
A22: Marks & Nos. | B22: No & Kinds of Pkgs Description of Goods | E22: Quantity | F22: Rate | G22: Amount | H22: Rate | I22: Taxable Amount | J22: GST Rate | K22: GST Amount
A23: GDW NOS : | B23: 421 PACKAGES (343 CARTONS & 78 HDP BUNDLES) CONTAINING | F23: FOB MUMBAI IN US$ | H23: FOB MUMBAI IN INR
A24: 2001 - 2421 | B24: PLASTIC (PP) EXTRUDED PIPES, PLASTIC (PP) & | H24: EX. RATE @ Rs.92.50
A25: 2421 | B25: (PA) MOULDED FITTINGS & CORRUGATED BOXES
B26: PLASTIC (PP) EXTRUDED PIPES : BOTH SIDE THREADED PIPES (HSN CODE : 3917.2200)
B27: CODE | C27: SIZE (IN / MM) | D27: LEN (MM) | E27: PIECES | F27: PER PC
B28: PP1509 | C28: 15 | D28: 225 | E28: 6000 | F28: 0.07 | G28: =E28*F28 -> 420 | H28: =I28/E28 -> 6.475 | I28: 38850 | J28: 0.18 | K28: =ROUND(I28*J28,) -> 6993
B29: PP1518 | C29: 15 | D29: 457 | E29: 7200 | F29: 0.24 | G29: =E29*F29 -> 1728 | H29: =I29/E29 -> 22.2 | I29: 159840 | J29: 0.18 | K29: =ROUND(I29*J29,) -> 28771
B30: 90441400 | C30: 1/2" | D30: 450 | E30: 2600 | F30: 0.24 | G30: =E30*F30 -> 624 | H30: =I30/E30 -> 22.2 | I30: 57720 | J30: 0.18 | K30: =ROUND(I30*J30,) -> 10390
B31: PP1524 | C31: 15 | D31: 610 | E31: 2300 | F31: 0.3 | G31: =E31*F31 -> 690 | H31: =I31/E31 -> 27.75 | I31: 63825 | J31: 0.18 | K31: =ROUND(I31*J31,) -> 11489
B32: 90441600 | C32: 1/2" | D32: 600 | E32: 1600 | F32: 0.31 | G32: =E32*F32 -> 496 | H32: =I32/E32 -> 28.675 | I32: 45880 | J32: 0.18 | K32: =ROUND(I32*J32,) -> 8258
B33: PE1536 | C33: 15 | D33: 915 | E33: 1000 | F33: 0.41 | G33: =E33*F33 -> 410 | H33: =I33/E33 -> 37.925 | I33: 37925 | J33: 0.18 | K33: =ROUND(I33*J33,) -> 6827
B34: 90441800 | C34: 1/2" | D34: 900 | E34: 700 | F34: 0.44 | G34: =E34*F34 -> 308 | H34: =I34/E34 -> 40.7 | I34: 28490 | J34: 0.18 | K34: =ROUND(I34*J34,) -> 5128
B35: PE1548 | C35: 15 | D35: 1220 | E35: 50 | F35: 0.53 | G35: =E35*F35 -> 26.5 | H35: =I35/E35 -> 49.025 | I35: 2451.25 | J35: 0.18 | K35: =ROUND(I35*J35,) -> 441
B36: PP2004 | C36: 20 | D36: 100 | E36: 500 | F36: 0.13 | G36: =E36*F36 -> 65 | H36: =I36/E36 -> 12.025 | I36: 6012.5 | J36: 0.18 | K36: =ROUND(I36*J36,) -> 1082
B37: 90447000 | C37: 3/4" | D37: 240 | E37: 4000 | F37: 0.22 | G37: =E37*F37 -> 880 | H37: =I37/E37 -> 20.35 | I37: 81400 | J37: 0.18 | K37: =ROUND(I37*J37,) -> 14652
B38: PE2018 | C38: 20 | D38: 457 | E38: 400 | F38: 0.35 | G38: =E38*F38 -> 140 | H38: =I38/E38 -> 32.375 | I38: 12950 | J38: 0.18 | K38: =ROUND(I38*J38,) -> 2331
B39: 90442400 | C39: 3/4" | D39: 450 | E39: 1600 | F39: 0.36 | G39: =E39*F39 -> 576 | H39: =I39/E39 -> 33.3 | I39: 53280 | J39: 0.18 | K39: =ROUND(I39*J39,) -> 9590
B40: PE2024 | C40: 20 | D40: 610 | E40: 1000 | F40: 0.45 | G40: =E40*F40 -> 450 | H40: =I40/E40 -> 41.625 | I40: 41625 | J40: 0.18 | K40: =ROUND(I40*J40,) -> 7493
B41: 90442700 | C41: 3/4" | D41: 750 | E41: 500 | F41: 0.56 | G41: =E41*F41 -> 280 | H41: =I41/E41 -> 51.8 | I41: 25900 | J41: 0.18 | K41: =ROUND(I41*J41,) -> 4662
B42: PP2508 | C42: 25 | D42: 200 | E42: 600 | F42: 0.24 | G42: =E42*F42 -> 144 | H42: =I42/E42 -> 22.2 | I42: 13320 | J42: 0.18 | K42: =ROUND(I42*J42,) -> 2398
B43: 90448000 | C43: 1" | D43: 270 | E43: 500 | F43: 0.35 | G43: =E43*F43 -> 175 | H43: =I43/E43 -> 32.375 | I43: 16187.5 | J43: 0.18 | K43: =ROUND(I43*J43,) -> 2914
B44: PE2515 | C44: 25 | D44: 375 | E44: 1000 | F44: 0.39 | G44: =E44*F44 -> 390 | H44: =I44/E44 -> 36.075 | I44: 36075 | J44: 0.18 | K44: =ROUND(I44*J44,) -> 6494
B45: PE2518 | C45: 25 | D45: 457 | E45: 2300 | F45: 0.45 | G45: =E45*F45 -> 1035 | H45: =I45/E45 -> 41.625 | I45: 95737.5 | J45: 0.18 | K45: =ROUND(I45*J45,) -> 17233
B46: 90443400 | C46: 1" | D46: 450 | E46: 800 | F46: 0.46 | G46: =E46*F46 -> 368 | H46: =I46/E46 -> 42.55 | I46: 34040 | J46: 0.18 | K46: =ROUND(I46*J46,) -> 6127
B47: PE2524 | C47: 25 | D47: 610 | E47: 400 | F47: 0.58 | G47: =E47*F47 -> 232 | H47: =I47/E47 -> 53.65 | I47: 21460 | J47: 0.18 | K47: =ROUND(I47*J47,) -> 3863
B48: 90443600 | C48: 1" | D48: 600 | E48: 500 | F48: 0.6 | G48: =E48*F48 -> 300 | H48: =I48/E48 -> 55.5 | I48: 27750 | J48: 0.18 | K48: =ROUND(I48*J48,) -> 4995
B49: 90443700 | C49: 1" | D49: 750 | E49: 500 | F49: 0.72 | G49: =E49*F49 -> 360 | H49: =I49/E49 -> 66.6 | I49: 33300 | J49: 0.18 | K49: =ROUND(I49*J49,) -> 5994
B50: 90443900 | C50: 1" | D50: 1800 | E50: 200 | F50: 1.66 | G50: =E50*F50 -> 332 | H50: =I50/E50 -> 153.55 | I50: 30710 | J50: 0.18 | K50: =ROUND(I50*J50,) -> 5528
B51: PE3206 | C51: 32 | D51: 150 | E51: 600 | F51: 0.28 | G51: =E51*F51 -> 168 | H51: =I51/E51 -> 25.9 | I51: 15540 | J51: 0.18 | K51: =ROUND(I51*J51,) -> 2797
B52: 90446200 | C52: 1-1/4" | D52: 150 | E52: 300 | F52: 0.29 | G52: =E52*F52 -> 87 | H52: =I52/E52 -> 26.825 | I52: 8047.5 | J52: 0.18 | K52: =ROUND(I52*J52,) -> 1449
B53: PE3218 | C53: 32 | D53: 450 | E53: 100 | F53: 0.6 | G53: =E53*F53 -> 60 | H53: =I53/E53 -> 55.5 | I53: 5550 | J53: 0.18 | K53: =ROUND(I53*J53,) -> 999
B54: 90446400 | C54: 1-1/4" | D54: 450 | E54: 100 | F54: 0.63 | G54: =E54*F54 -> 63 | H54: =I54/E54 -> 58.275 | I54: 5827.5 | J54: 0.18 | K54: =ROUND(I54*J54,) -> 1049
B55: 90446600 | C55: 1-1/4" | D55: 600 | E55: 200 | F55: 0.8 | G55: =E55*F55 -> 160 | H55: =I55/E55 -> 74 | I55: 14800 | J55: 0.18 | K55: =ROUND(I55*J55,) -> 2664
B56: PE3230 | C56: 32 | D56: 750 | E56: 60 | F56: 0.93 | G56: =E56*F56 -> 55.8 | H56: =I56/E56 -> 86.025 | I56: 5161.5 | J56: 0.18 | K56: =ROUND(I56*J56,) -> 929
B57: 90446700 | C57: 1-1/4" | D57: 900 | E57: 100 | F57: 1.15 | G57: =E57*F57 -> 115 | H57: =I57/E57 -> 106.375 | I57: 10637.5 | J57: 0.18 | K57: =ROUND(I57*J57,) -> 1915
B58: 90446800 | C58: 1-1/4" | D58: 1800 | E58: 50 | F58: 2.2 | G58: =E58*F58 -> 110 | H58: =I58/E58 -> 203.5 | I58: 10175 | J58: 0.18 | K58: =ROUND(I58*J58,) -> 1832
B59: 90447200 | C59: 1-1/2" | D59: 150 | E59: 300 | F59: 0.34 | G59: =E59*F59 -> 102 | H59: =I59/E59 -> 31.45 | I59: 9435 | J59: 0.18 | K59: =ROUND(I59*J59,) -> 1698
B60: PE4008 | C60: 40 | D60: 200 | E60: 150 | F60: 0.44 | G60: =E60*F60 -> 66 | H60: =I60/E60 -> 40.7 | I60: 6105 | J60: 0.18 | K60: =ROUND(I60*J60,) -> 1099
B61: PE4018 | C61: 40 | D61: 450 | E61: 100 | F61: 0.81 | G61: =E61*F61 -> 81 | H61: =I61/E61 -> 74.925 | I61: 7492.5 | J61: 0.18 | K61: =ROUND(I61*J61,) -> 1349
B62: 90447400 | C62: 1-1/2" | D62: 450 | E62: 200 | F62: 0.86 | G62: =E62*F62 -> 172 | H62: =I62/E62 -> 79.55 | I62: 15910 | J62: 0.18 | K62: =ROUND(I62*J62,) -> 2864
B63: PE5006 | C63: 50 | D63: 150 | E63: 150 | F63: 0.41 | G63: =E63*F63 -> 61.5 | H63: =I63/E63 -> 37.925 | I63: 5688.75 | J63: 0.18 | K63: =ROUND(I63*J63,) -> 1024
B64: 90448200 | C64: 2" | D64: 150 | E64: 150 | F64: 0.42 | G64: =E64*F64 -> 63 | H64: =I64/E64 -> 38.85 | I64: 5827.5 | J64: 0.18 | K64: =ROUND(I64*J64,) -> 1049
B65: 90448300 | C65: 2" | D65: 300 | E65: 75 | F65: 0.75 | G65: =E65*F65 -> 56.25 | H65: =I65/E65 -> 69.375 | I65: 5203.125 | J65: 0.18 | K65: =ROUND(I65*J65,) -> 937
B66: PE5018 | C66: 50 | D66: 450 | E66: 100 | F66: 1.02 | G66: =E66*F66 -> 102 | H66: =I66/E66 -> 94.35 | I66: 9435 | J66: 0.18 | K66: =ROUND(I66*J66,) -> 1698
B67: 90448400 | C67: 2" | D67: 450 | E67: 100 | F67: 1.07 | G67: =E67*F67 -> 107 | H67: =I67/E67 -> 98.975 | I67: 9897.5 | J67: 0.18 | K67: =ROUND(I67*J67,) -> 1782
B68: 90448800 | C68: 2" | D68: 1200 | E68: 50 | F68: 2.69 | G68: =E68*F68 -> 134.5 | H68: =I68/E68 -> 248.825 | I68: 12441.25 | J68: 0.18 | K68: =ROUND(I68*J68,) -> 2239
B69: 90448820 | C69: 2" | D69: 1800 | E69: 60 | F69: 4.02 | G69: =E69*F69 -> 241.2 | H69: =I69/E69 -> 371.85 | I69: 22311 | J69: 0.18 | K69: =ROUND(I69*J69,) -> 4016
B70: PLASTIC (PP) EXTRUDED PIPES : M / F THREADED PIPES (HSN CODE : 3917.2200)
B71: PMF2524 | C71: 25 | D71: 600 | E71: 100 | F71: 0.6 | G71: =E71*F71 -> 60 | H71: =I71/E71 -> 55.5 | I71: 5550 | J71: 0.18 | K71: =ROUND(I71*J71,) -> 999
B72: 90445600 | C72: 1" | D72: 600 | E72: 500 | F72: 0.63 | G72: =E72*F72 -> 315 | H72: =I72/E72 -> 58.275 | I72: 29137.5 | J72: 0.18 | K72: =ROUND(I72*J72,) -> 5245
B73: 90445700 | C73: 1" | D73: 750 | E73: 200 | F73: 0.77 | G73: =E73*F73 -> 154 | H73: =I73/E73 -> 71.225 | I73: 14245 | J73: 0.18 | K73: =ROUND(I73*J73,) -> 2564
B74: PMF2536 | C74: 25 | D74: 900 | E74: 200 | F74: 0.86 | G74: =E74*F74 -> 172 | H74: =I74/E74 -> 79.55 | I74: 15910 | J74: 0.18 | K74: =ROUND(I74*J74,) -> 2864
B75: 90445800 | C75: 1" | D75: 900 | E75: 200 | F75: 0.89 | G75: =E75*F75 -> 178 | H75: =I75/E75 -> 82.325 | I75: 16465 | J75: 0.18 | K75: =ROUND(I75*J75,) -> 2964
B76: PLASTIC (PP) MOULDED FITTINGS (HSN CODE : 3917.4000)
B77: CODE | C77: SIZE (IN / MM) | E77: PIECES | F77: PER 100 PCS
B78: PET1512 | C78: 15 | E78: 300 | F78: 14.4 | G78: =E78*F78/100 -> 43.2 | H78: =I78/E78 -> 13.32 | I78: 3996 | J78: 0.18 | K78: =ROUND(I78*J78,) -> 719
B79: PP1501 / 5 | C79: 15 | E79: 4000 | F79: 13.8 | G79: =E79*F79/100 -> 552 | H79: =I79/E79 -> 12.765 | I79: 51060 | J79: 0.18 | K79: =ROUND(I79*J79,) -> 9191
B82: Total C/F Page :2 | G82: =SUM(G28:G81) -> 13908.95 | I82: =SUM(I28:I81) -> 1286577.9 | K82: =SUM(K28:K81) -> 231588
A83: GSTIN : 27AVIPS4808H1Z8 w.e.f 20.01.2021 | H83: FOR JAIKVIN GLOBAL
A84: PAN No: AVIPS4808H
A85: Declaration:-
A86: We declare that this invoice shows the actual price of the goods described and that all particulars are true and correct.
A87: SUPPLY MEANT FOR EXPORT WITH PAYMENT OF INTEGRATED TAX
A88: We intend to claim rewards under RoDTEP | H88: PROPRIETOR

Sheet Page2
A1: =Page1!A1 -> MERCHANT | B1: =Page1!B1 -> INVOICE | K1: Page 2
A2: =Page1!A2 -> JAIKVIN GLOBAL | F2: =Page1!F2 -> Invoice No. | G2: =Page1!G2 -> JG/26-27/6002 DT 04.05.2026 | K2: =Page1!K2 -> Exporter's Ref.
F3: =Page1!F3 -> Date: | G3: =Page1!G3 -> 0 | K3: =Page1!K3 -> IEC AVIPS4808H
A4: =Page1!A4 -> Merchant Exporters | F4: =Page1!F4 -> Buyers Order No: | H4: =Page1!H4 -> JG/26-P/09 DT 27.04.2026
A5: =Page1!A5 -> A-101, Rajshree Royale, Navroji Lane, Ghatkopar (W), | F5: =Page1!F5 | H5: =Page1!H5 -> 0
A6: =Page1!A6 -> MUMBAI-400 086. Maharashtra (State Code : 27) | F6: =Page1!F6 -> Other Reference(s): | H6: =Page1!H6 -> 0
A7: =Page1!A7 -> Tel: 9987122600 E-Mail: aalok.shah@jaikvinglobal.com | F7: =Page1!F7 | H7: =Page1!H7 -> 0
A8: =Page1!A8 -> On Account & Risks of: | C8: =Page1!C8 -> 0 | F8: =Page1!F8 -> IRN No | G8: =Page1!G8 -> 5049ef43c7126a4c35bf29795ce49390de0338
A9: =Page1!A9 -> Messrs Corecomp Pty Ltd., | F9: =Page1!F9 -> 0 | G9: =Page1!G9 -> c2897a4b4929c186580cfacad7
A10: =Page1!A10 -> T/A G.D.Watermark | F10: =Page1!F10 -> Ack No | G10: =Page1!G10 -> 122632432448548
A11: =Page1!A11 -> 13, Tesla Link, | F11: =Page1!F11 -> 0 | G11: =Page1!G11 -> 0
A12: =Page1!A12 -> Wangara WA 6065 (Australia) | F12: =Page1!F12 -> Ack Dt | G12: =Page1!G12 -> 04-05-2026 3:51:00 PM
A13: =Page1!A13 -> Invoice of: | B13: =Page1!B13 -> PLASTIC (PP) EXTRUDED PIPES, PLASTIC (PP) | F13: =Page1!F13 -> Country of Origin | I13: =Page1!I13 -> Country of Final Destination
A14: =Page1!A14 | B14: =Page1!B14 -> & (PA) MOULDED FITTINGS AND CORRUGATED | F14: =Page1!F14 -> INDIA | I14: =Page1!I14 -> AUSTRALIA
A15: =Page1!A15 | B15: =Page1!B15 -> BOXES | F15: =Page1!F15 -> BL. NO. | G15: =Page1!G15 -> SFPM2605165498 DT. 19.05.2026 | H15: =Page1!H15 -> 0 | I15: =Page1!I15 -> 0 | J15: =Page1!J15 -> 0 | K15: =Page1!K15 -> 0
A16: =Page1!A16 -> Pre-Carraige by: | C16: =Page1!C16 -> Place of Receipt by Pre-Carraige | F16: =Page1!F16 -> Shipped Per | G16: =Page1!G16 -> CAPE SYROS VOYAGE 092E | H16: =Page1!H16 -> 0 | I16: =Page1!I16 -> 0 | J16: =Page1!J16 -> 0 | K16: =Page1!K16 -> 0
A17: =Page1!A17 | C17: =Page1!C17 -> 0 | F17: =Page1!F17 -> S/B No: | G17: =Page1!G17 -> 2945305 DT. 04.05.2026 | H17: =Page1!H17 -> 0 | I17: =Page1!I17 -> 0 | J17: =Page1!J17 -> 0 | K17: =Page1!K17 -> 0
A18: =Page1!A18 -> Shipped per: | C18: =Page1!C18 -> Port of Loading: | F18: =Page1!F18 -> Terms of Delivery: | H18: =Page1!H18 -> FOB MUMBAI
A19: =Page1!A19 -> CAPE SYROS VOYAGE 092E | C19: =Page1!C19 -> NHAVA SHEVA-MUMBAI (INDIA) | F19: =Page1!F19 -> Terms of Payment: | H19: =Page1!H19 -> D.P.SIGHT DRAFT
A20: =Page1!A20 -> Port of Discharge: | C20: =Page1!C20 -> Port of destination | F20: =Page1!F20 -> Through: | H20: =Page1!H20 -> HDFC BANK LTD, GHATKOPAR (E) BRANCH
A21: =Page1!A21 -> FREMANTLE | C21: =Page1!C21 -> FREMANTLE | F21: =Page1!F21 -> 0 | H21: =Page1!H21 -> GHATKOPAR (E), MUMBAI 400 077 (INDIA)
A22: Marks & Nos. | B22: No & Kinds of Pkgs Description of Goods | E22: Quantity | F22: Rate | G22: Amount | H22: Rate | I22: Taxable Amount | J22: GST Rate | K22: GST Amount
A23: =Page1!A23 -> GDW NOS : | B23: =Page1!B23 -> 421 PACKAGES (343 CARTONS & 78 HDP BUNDLES) CONTAINING | F23: =Page1!F23 -> FOB MUMBAI IN US$ | H23: =Page1!H23 -> FOB MUMBAI IN INR | J23: =Page1!J23 -> 0
A24: =Page1!A24 -> 2001 - 2421 | B24: =Page1!B24 -> PLASTIC (PP) EXTRUDED PIPES, PLASTIC (PP) & | H24: =Page1!H24 -> EX. RATE @ Rs.92.50 | J24: =Page1!J24 -> 0
A25: =Page1!A25 -> 2421 | B25: =Page1!B25 -> (PA) MOULDED FITTINGS & CORRUGATED BOXES | F25: BAL B/F… | G25: =Page1!G82 -> 13908.95 | I25: =Page1!I82 -> 1286577.9 | J25: =Page1!J25 -> 0 | K25: =Page1!K82 -> 231588
A26: =Page1!A26 -> 0 | B26: PLASTIC (PA) MOULDED FITTINGS (HSN CODE : 3917.4000)
A27: =Page1!A27 -> 0 | B27: CODE | C27: SIZE (IN / MM) | E27: PIECES | F27: PER 100 PCS
B28: GRC15 | C28: 15 | E28: 10000 | F28: 9.6 | G28: =E28*F28/100 -> 960 | H28: =I28/E28 -> 8.88 | I28: 88800 | J28: 0.18 | K28: =ROUND(I28*J28,) -> 15984
B29: GRC20 | C29: 20 | E29: 3000 | F29: 12 | G29: =E29*F29/100 -> 360 | H29: =I29/E29 -> 11.1 | I29: 33300 | J29: 0.18 | K29: =ROUND(I29*J29,) -> 5994
B30: GRC25 | C30: 25 | E30: 900 | F30: 15.6 | G30: =E30*F30/100 -> 140.4 | H30: =I30/E30 -> 14.43 | I30: 12987 | J30: 0.18 | K30: =ROUND(I30*J30,) -> 2338
A31: Container No. | B31: GRMFE25 | C31: 25 | E31: 1400 | F31: 33.6 | G31: =E31*F31/100 -> 470.4 | H31: =I31/E31 -> 31.08 | I31: 43512 | J31: 0.18 | K31: =ROUND(I31*J31,) -> 7832
A32: OOCU0793142 | B32: GRRS2015 | C32: 20*15 | E32: 1800 | F32: 21.6 | G32: =E32*F32/100 -> 388.8 | H32: =I32/E32 -> 19.98 | I32: 35964 | J32: 0.18 | K32: =ROUND(I32*J32,) -> 6474
B33: GRRS2520 | C33: 25*20 | E33: 1650 | F33: 24 | G33: =E33*F33/100 -> 396 | H33: =I33/E33 -> 22.2 | I33: 36630 | J33: 0.18 | K33: =ROUND(I33*J33,) -> 6593
B34: GRS25 | C34: 25 | E34: 500 | F34: 22.8 | G34: =E34*F34/100 -> 114 | H34: =I34/E34 -> 21.09 | I34: 10545 | J34: 0.18 | K34: =ROUND(I34*J34,) -> 1898
B35: GRT15 | C35: 15 | E35: 2160 | F35: 33.6 | G35: =E35*F35/100 -> 725.76 | H35: =I35/E35 -> 31.08 | I35: 67132.8 | J35: 0.18 | K35: =ROUND(I35*J35,) -> 12084
B36: GRT20 | C36: 20 | E36: 700 | F36: 40.8 | G36: =E36*F36/100 -> 285.6 | H36: =I36/E36 -> 37.74 | I36: 26418 | J36: 0.18 | K36: =ROUND(I36*J36,) -> 4755
B37: GRT25 | C37: 25 | E37: 1760 | F37: 50.4 | G37: =E37*F37/100 -> 887.04 | H37: =I37/E37 -> 46.62 | I37: 82051.2 | J37: 0.18 | K37: =ROUND(I37*J37,) -> 14769
B38: GRT32 | C38: 32 | E38: 1000 | F38: 91.2 | G38: =E38*F38/100 -> 912 | H38: =I38/E38 -> 84.36 | I38: 84360 | J38: 0.18 | K38: =ROUND(I38*J38,) -> 15185
B39: CORRUGATED BOXES (HSN CODE : 4819.1010)
B40: CODE | C40: SIZE ( MM) | E40: PIECES | F40: PER PC
A41: Seal No. | B41: GD3 | C41: 570 X 368 X 178 | E41: 750 | F41: 0.85 | G41: =E41*F41 -> 637.5 | H41: =I41/E41 -> 78.625 | I41: 58968.75 | J41: 0.05 | K41: =ROUND(I41*J41,) -> 2948
A42: IND-0054079 | B42: GD4 | C42: 570 X 368 X 267 | E42: 277 | F42: 0.85 | G42: =E42*F42 -> 235.45 | H42: =I42/E42 -> 78.625 | I42: 21779.125 | J42: 0.05 | K42: =ROUND(I42*J42,) -> 1089
A50: Nett Wt.
A51: 6050.915
A52: KGS
A59: Gross Wt
A60: 6400
A61: KGS
A67: Freight
A68: Payable at
A69: Destination
A73: FOB VALUE
A74: =G75 -> 20421.9
A75: =I75 -> 1889025.8 | B75: Total FOB Mumbai Value : | G75: =SUM(G25:G74) -> 20421.9 | I75: =SUM(I25:I74) -> 1889025.8 | K75: =SUM(K25:K74) -> 329531
B76: BREAKUP OF GST | D76: UOM | E76: VALUE (US$) | F76: TAXABLE VALUE (INR) | H76: CGST | I76: SGST | J76: IGST | K76: TOTAL GST
B77: HSN CODE : 3917.2200 | D77: =SUM(Page1!E28:E69,Page1!E71:E75) -> 40395 | E77: =SUM(Page1!G28:G69,Page1!G71:G75) -> 13313.75 | F77: =SUM(Page1!I28:I75) -> 1231521.9 | H77: 0 | I77: 0 | J77: =SUM(Page1!K28:K75) -> 221678 | K77: =SUM(H77:J77) -> 221678
B78: HSN CODE : 3917.4000 | D78: =SUM(Page1!E78:E79)+SUM(Page2!E28:E38) -> 29170 | E78: =SUM(Page1!G78:G79)+SUM(Page2!G28:G38) -> 6235.2 | F78: =SUM(I28:I38)+SUM(Page1!I78:I79) -> 576756 | H78: 0 | I78: 0 | J78: =SUM(K28:K38)+SUM(Page1!K78:K79) -> 103816 | K78: =SUM(H78:J78) -> 103816
B79: HSN CODE : 4819.1010 | D79: =SUM(E41:E42) -> 1027 | E79: =SUM(G41:G42) -> 872.95 | F79: =SUM(I41:I42) -> 80747.875 | H79: 0 | I79: 0 | J79: =SUM(K41:K42) -> 4037 | K79: =SUM(H79:J79) -> 4037
B80: TOTAL | D80: =SUM(D77:D79) -> 70592 | E80: =SUM(E77:E79) -> 20421.9 | F80: =SUM(F77:F79) -> 1889025.8 | G80: =SUM(G77:G79) -> 0 | H80: =SUM(H77:H79) -> 0 | I80: =SUM(I77:I79) -> 0 | J80: =SUM(J77:J79) -> 329531 | K80: =SUM(K77:K79) -> 329531
B81: US DOLLARS TWENTY THOUSAND FOUR HUNDRED TWENTY ONE AND CENTS NINETY ONLY
B82: INDIAN RUPEES EIGHTEEN LAKH EIGHTY NINE THOUSAND TWENTY FIVE AND PAISE SEVENTY FIVE ONLY
A83: GSTIN : 27AVIPS4808H1Z8 w.e.f 20.01.2021 | H83: FOR JAIKVIN GLOBAL
A84: PAN No: AVIPS4808H
A85: Declaration:-
A86: We declare that this invoice shows the actual price of the goods described and that all particulars are true and correct.
A87: SUPPLY MEANT FOR EXPORT WITH PAYMENT OF INTEGRATED TAX
A88: We intend to claim rewards under RoDTEP | H88: PROPRIETOR

Sheet Annx
A8: ANNEXTURE TO INVOICE
A10: Inv No & Dt | B10: =Page1!G2 -> JG/26-27/6002 DT 04.05.2026 | C10: NO OF PKGS | D10: 421 | E10: Shipment to | F10: FREMANTLE
A12: ITEM CODE | C12: QUANTITY | D12: FOB / PC US$ | F12: NET WT | G12: RATE / KG
A13: PLASTIC (PP) EXTRUDED PIPES : BOTH SIDE THREADED PIPES | C13: PCS | D13: Unit | E13: Total | F13: KGS | G13: US$
A14: PP1509 | C14: 6000 | D14: 0.07 | E14: =C14*D14 -> 420 | F14: 242.1 | G14: =E14/F14 -> 1.7348203
A15: PP1518 | C15: 7200 | D15: 0.24 | E15: =C15*D15 -> 1728 | F15: 581.04 | G15: =E15/F15 -> 2.9739777
A16: 90441400 | C16: 2600 | D16: 0.24 | E16: =C16*D16 -> 624 | F16: 209.82 | G16: =E16/F16 -> 2.9739777
A17: PP1524 | C17: 2300 | D17: 0.3 | E17: =C17*D17 -> 690 | F17: 247.25 | G17: =E17/F17 -> 2.7906977
A18: 90441600 | C18: 1600 | D18: 0.31 | E18: =C18*D18 -> 496 | F18: 172 | G18: =E18/F18 -> 2.8837209
A19: PE1536 | C19: 1000 | D19: 0.41 | E19: =C19*D19 -> 410 | F19: 161.4 | G19: =E19/F19 -> 2.5402726
A20: 90441800 | C20: 700 | D20: 0.44 | E20: =C20*D20 -> 308 | F20: 112.98 | G20: =E20/F20 -> 2.7261462
A21: PE1548 | C21: 50 | D21: 0.53 | E21: =C21*D21 -> 26.5 | F21: 10.75 | G21: =E21/F21 -> 2.4651163
A22: PP2004 | C22: 500 | D22: 0.13 | E22: =C22*D22 -> 65 | F22: 14 | G22: =E22/F22 -> 4.6428571
A23: 90447000 | C23: 4000 | D23: 0.22 | E23: =C23*D23 -> 880 | F23: 256 | G23: =E23/F23 -> 3.4375
A24: PE2018 | C24: 400 | D24: 0.35 | E24: =C24*D24 -> 140 | F24: 52 | G24: =E24/F24 -> 2.6923077
A25: 90442400 | C25: 1600 | D25: 0.36 | E25: =C25*D25 -> 576 | F25: 208 | G25: =E25/F25 -> 2.7692308
A26: PE2024 | C26: 1000 | D26: 0.45 | E26: =C26*D26 -> 450 | F26: 170 | G26: =E26/F26 -> 2.6470588
A27: 90442700 | C27: 500 | D27: 0.56 | E27: =C27*D27 -> 280 | F27: 110 | G27: =E27/F27 -> 2.5454545
A28: PP2508 | C28: 600 | D28: 0.24 | E28: =C28*D28 -> 144 | F28: 43.2 | G28: =E28/F28 -> 3.3333333
A29: 90448000 | C29: 500 | D29: 0.35 | E29: =C29*D29 -> 175 | F29: 49.3 | G29: =E29/F29 -> 3.5496957
A30: PE2515 | C30: 1000 | D30: 0.39 | E30: =C30*D30 -> 390 | F30: 137 | G30: =E30/F30 -> 2.8467153
A31: PE2518 | C31: 2300 | D31: 0.45 | E31: =C31*D31 -> 1035 | F31: 391 | G31: =E31/F31 -> 2.6470588
A32: 90443400 | C32: 800 | D32: 0.46 | E32: =C32*D32 -> 368 | F32: 136 | G32: =E32/F32 -> 2.7058824
A33: PE2524 | C33: 400 | D33: 0.58 | E33: =C33*D33 -> 232 | F33: 94 | G33: =E33/F33 -> 2.4680851
A34: 90443600 | C34: 500 | D34: 0.6 | E34: =C34*D34 -> 300 | F34: 117.5 | G34: =E34/F34 -> 2.5531915
A35: 90443700 | C35: 500 | D35: 0.72 | E35: =C35*D35 -> 360 | F35: 143 | G35: =E35/F35 -> 2.5174825
A36: 90443900 | C36: 200 | D36: 1.66 | E36: =C36*D36 -> 332 | F36: 132 | G36: =E36/F36 -> 2.5151515
A37: PE3206 | C37: 600 | D37: 0.28 | E37: =C37*D37 -> 168 | F37: 45 | G37: =E37/F37 -> 3.7333333
A38: 90446200 | C38: 300 | D38: 0.29 | E38: =C38*D38 -> 87 | F38: 22.5 | G38: =E38/F38 -> 3.8666667
A39: PE3218 | C39: 100 | D39: 0.6 | E39: =C39*D39 -> 60 | F39: 22.5 | G39: =E39/F39 -> 2.6666667
A40: 90446400 | C40: 100 | D40: 0.63 | E40: =C40*D40 -> 63 | F40: 22.5 | G40: =E40/F40 -> 2.8
A41: 90446600 | C41: 200 | D41: 0.8 | E41: =C41*D41 -> 160 | F41: 60 | G41: =E41/F41 -> 2.6666667
A42: PE3230 | C42: 60 | D42: 0.93 | E42: =C42*D42 -> 55.8 | F42: 19.1 | G42: =E42/F42 -> 2.921466
A43: 90446700 | C43: 100 | D43: 1.15 | E43: =C43*D43 -> 115 | F43: 45 | G43: =E43/F43 -> 2.5555556
A44: 90446800 | C44: 50 | D44: 2.2 | E44: =C44*D44 -> 110 | F44: 45.8 | G44: =E44/F44 -> 2.4017467
A45: 90447200 | C45: 300 | D45: 0.34 | E45: =C45*D45 -> 102 | F45: 29.9 | G45: =E45/F45 -> 3.4113712
A46: PE4008 | C46: 150 | D46: 0.44 | E46: =C46*D46 -> 66 | F46: 20.8 | G46: =E46/F46 -> 3.1730769
A47: PE4018 | C47: 100 | D47: 0.81 | E47: =C47*D47 -> 81 | F47: 29.9 | G47: =E47/F47 -> 2.7090301
A48: 90447400 | C48: 200 | D48: 0.86 | E48: =C48*D48 -> 172 | F48: 59.8 | G48: =E48/F48 -> 2.8762542
A49: PE5006 | C49: 150 | D49: 0.41 | E49: =C49*D49 -> 61.5 | F49: 21 | G49: =E49/F49 -> 2.9285714
A50: 90448200 | C50: 150 | D50: 0.42 | E50: =C50*D50 -> 63 | F50: 21 | G50: =E50/F50 -> 3
A51: 90448300 | C51: 75 | D51: 0.75 | E51: =C51*D51 -> 56.25 | F51: 21 | G51: =E51/F51 -> 2.6785714
A52: PE5018 | C52: 100 | D52: 1.02 | E52: =C52*D52 -> 102 | F52: 42 | G52: =E52/F52 -> 2.4285714
A53: 90448400 | C53: 100 | D53: 1.07 | E53: =C53*D53 -> 107 | F53: 42 | G53: =E53/F53 -> 2.547619
A54: 90448800 | C54: 50 | D54: 2.69 | E54: =C54*D54 -> 134.5 | F54: 52.2 | G54: =E54/F54 -> 2.5766284
A55: 90448820 | C55: 60 | D55: 4.02 | E55: =C55*D55 -> 241.2 | F55: 92.4 | G55: =E55/F55 -> 2.6103896
A65: ITEM CODE | C65: QUANTITY | D65: FOB / PC US$ | F65: NET WT | G65: RATE / KG
A66: PLASTIC (PP) EXTRUDED PIPES : M / F THREADED PIPES | C66: PCS | D66: Unit | E66: Total | F66: KGS | G66: US$
A67: PMF2524 | C67: 100 | D67: 0.6 | E67: =C67*D67 -> 60 | F67: 23.5 | G67: =E67/F67 -> 2.5531915
A68: 90445600 | C68: 500 | D68: 0.63 | E68: =C68*D68 -> 315 | F68: 117.5 | G68: =E68/F68 -> 2.6808511
A69: 90445700 | C69: 200 | D69: 0.77 | E69: =C69*D69 -> 154 | F69: 57.2 | G69: =E69/F69 -> 2.6923077
A70: PMF2536 | C70: 200 | D70: 0.86 | E70: =C70*D70 -> 172 | F70: 68 | G70: =E70/F70 -> 2.5294118
A71: 90445800 | C71: 200 | D71: 0.89 | E71: =C71*D71 -> 178 | F71: 68 | G71: =E71/F71 -> 2.6176471
A73: ITEM CODE | C73: QUANTITY | D73: FOB / 100 PCS US$ | F73: NET WT | G73: RATE / KG
A74: PLASTIC (PP) MOULDED FITTINGS | C74: PCS | D74: Unit | E74: Total | F74: KGS | G74: US$
A75: PET1512 | C75: 300 | D75: 14.4 | E75: =C75*D75/100 -> 43.2 | F75: 11.5 | G75: =E75/F75 -> 3.7565217
A76: PP1501 / 5 | C76: 4000 | D76: 13.8 | E76: =C76*D76/100 -> 552 | F76: 17.6 | G76: =E76/F76 -> 31.363636
A78: ITEM CODE | C78: QUANTITY | D78: FOB / 100 PCS US$ | F78: NET WT | G78: RATE / KG
A79: PLASTIC (PA) MOULDED FITTINGS | C79: PCS | D79: Unit | E79: Total | F79: KGS | G79: US$
A80: GRC15 | C80: 10000 | D80: 9.6 | E80: =C80*D80/100 -> 960 | F80: 100 | G80: =E80/F80 -> 9.6
A81: GRC20 | C81: 3000 | D81: 12 | E81: =C81*D81/100 -> 360 | F81: 36 | G81: =E81/F81 -> 10
A82: GRC25 | C82: 900 | D82: 15.6 | E82: =C82*D82/100 -> 140.4 | F82: 16.7 | G82: =E82/F82 -> 8.4071856
A83: GRMFE25 | C83: 1400 | D83: 33.6 | E83: =C83*D83/100 -> 470.4 | F83: 51.6 | G83: =E83/F83 -> 9.1162791
A84: GRRS2015 | C84: 1800 | D84: 21.6 | E84: =C84*D84/100 -> 388.8 | F84: 32 | G84: =E84/F84 -> 12.15
A85: GRRS2520 | C85: 1650 | D85: 24 | E85: =C85*D85/100 -> 396 | F85: 42.9 | G85: =E85/F85 -> 9.2307692
A86: GRS25 | C86: 500 | D86: 22.8 | E86: =C86*D86/100 -> 114 | F86: 16.3 | G86: =E86/F86 -> 6.993865
A87: GRT15 | C87: 2160 | D87: 33.6 | E87: =C87*D87/100 -> 725.76 | F87: 54 | G87: =E87/F87 -> 13.44
A88: GRT20 | C88: 700 | D88: 40.8 | E88: =C88*D88/100 -> 285.6 | F88: 28.2 | G88: =E88/F88 -> 10.12766
A89: GRT25 | C89: 1760 | D89: 50.4 | E89: =C89*D89/100 -> 887.04 | F89: 112 | G89: =E89/F89 -> 7.92
A90: GRT32 | C90: 1000 | D90: 91.2 | E90: =C90*D90/100 -> 912 | F90: 98 | G90: =E90/F90 -> 9.3061224
A92: ITEM CODE | C92: QUANTITY | D92: FOB / PC US$ | F92: NET WT | G92: RATE / KG
A93: CORRUGATED BOXES | C93: PCS | D93: Unit | E93: Total | F93: KGS | G93: US$
A94: GD3 | C94: 750 | D94: 0.85 | E94: 637.5 | F94: 408.5 | G94: =E94/F94 -> 1.5605875
A95: GD4 | C95: 277 | D95: 0.85 | E95: 235.45 | F95: 186.675 | G95: =E95/F95 -> 1.261283
A97: TOTAL | E97: =SUM(E14:E55)+SUM(E67:E71)+SUM(E75:E76)+SUM(E80:E90)+SUM(E94:E95) -> 20421.9 | F97: =SUM(F14:F55)+SUM(F67:F71)+SUM(F75:F76)+SUM(F80:F90)+SUM(F94:F95) -> 6050.915
