Workbook

Sheet VP
A8: COST SHEET
A9: (For Certificate of Origin to be issued to Manufacturer Exporter or Merchant Exporter)
A11: Inv No | B11: JG/26-27/6002 | F11: Date | G11: 04.05.2026
A13: Name of the Finished Product | F13: PLASTIC (PP) & (PA) MOULDED FITTINGS
A14: HS Code of the Product | F14: 3917.4000
A15: FOB Price / Ex-Work Price of Product | F15: 1034752.7
A16: 1. Value of imported / undetermined : Origin | F16: NIL
A17: raw material
A18: 2. Value of indigenous Raw Materials : | F18: =K41 -> 759268
A20: 3. Direct Cost of Processing | F20: =F18*8/100 -> 60741.44
A22: 4. Overhead & Indirect Cost of Processing | F22: =F15-F18-F20 -> 214743.27
A23: Including Profit
A25: (A) Details of Raw Materials of Imported / Undetermined Origin
A27: No | B27: Name of Materials | D27: Country of | E27: HS | F27: BE / invoice No | H27: Per Unit | I27: Quantity used | K27: Value of material
B28: Used | D28: Origin | E28: Code | F28: & Date | I28: in the Finished | K28: used in the
I29: Product | K29: Finished Product
B31: NOT APPLICABLE
I34: TOTAL
A36: (B) Details of Raw Materials of Indian Origin
A38: No | B38: Name of Materials | D38: Country of | E38: HS | F38: BE / invoice No | H38: Per Unit | I38: Quantity used | K38: Value of material
B39: Used | D39: Origin | E39: Code | F39: & Date | I39: in the Finished | K39: used in the
I40: Product | K40: Finished Product
A41: 1 | B41: POLYPROPYLENE | D41: INDIA | E41: 3902 | F41: 005 - DT 10.04.2026 | H41: PCS | I41: 1 | K41: 759268
I45: TOTAL | K45: =SUM(K41:L43) -> 759268
A47: Calculation of RVC/QVC/AIFTA Content as per the requirment of FTA / PTA / CEPA :
A49: Seal
A50: Stamp

Sheet HP
A8: COST SHEET
A9: (For Certificate of Origin to be issued to Manufacturer Exporter or Merchant Exporter)
A11: Inv No | B11: =VP!B11:E11 -> JG/26-27/6002 | F11: Date | G11: =VP!G11:J11 -> 04.05.2026
A13: Name of the Finished Product | F13: PLASTIC (PP) & (PA) MOULDED FITTINGS
A14: HS Code of the Product | F14: 3917.4000
A15: FOB Price / Ex-Work Price of Product | F15: 576756
A16: 1. Value of imported / undetermined : Origin | F16: NIL
A17: raw material
A18: 2. Value of indigenous Raw Materials : | F18: =K45 -> 366943
A20: 3. Direct Cost of Processing | F20: =F18*8/100 -> 29355.44
A22: 4. Overhead & Indirect Cost of Processing | F22: =F15-F18-F20 -> 180457.56
A23: Including Profit
A25: (A) Details of Raw Materials of Imported / Undetermined Origin
A27: No | B27: Name of Materials | D27: Country of | E27: HS | F27: BE / invoice No | H27: Per Unit | I27: Quantity used | K27: Value of material
B28: Used | D28: Origin | E28: Code | F28: & Date | I28: in the Finished | K28: used in the
I29: Product | K29: Finished Product
B31: NOT APPLICABLE
I34: TOTAL
A36: (B) Details of Raw Materials of Indian Origin
A38: No | B38: Name of Materials | D38: Country of | E38: HS | F38: BE / invoice No | H38: Per Unit | I38: Quantity used | K38: Value of material
B39: Used | D39: Origin | E39: Code | F39: & Date | I39: in the Finished | K39: used in the
I40: Product | K40: Finished Product
A41: 1 | B41: POLYPROPYLENE | D41: INDIA | E41: 3902 | F41: BH/19/26-27 | H41: PCS | I41: 1 | K41: 366943
F42: DT 02.05.2026
I45: TOTAL | K45: =SUM(K41:L43) -> 366943
A47: Calculation of RVC/QVC/AIFTA Content as per the requirment of FTA / PTA / CEPA :
A49: Seal
A50: Stamp
A51: Seal
A52: Stamp

Sheet KP
A8: COST SHEET
A9: (For Certificate of Origin to be issued to Manufacturer Exporter or Merchant Exporter)
A11: Inv No | B11: =VP!B11:E11 -> JG/26-27/6002 | F11: Date | G11: =VP!G11:J11 -> 04.05.2026
A13: Name of the Finished Product | F13: PLASTIC (PP) MOULDED FITTINGS
A14: HS Code of the Product | F14: 3917.4000
A15: FOB Price / Ex-Work Price of Product | F15: 215928.45
A16: 1. Value of imported / undetermined : Origin | F16: NIL
A17: raw material
A18: 2. Value of indigenous Raw Materials : | F18: =K45 -> 168363
A20: 3. Direct Cost of Processing | F20: =F18*8/100 -> 13469.04
A22: 4. Overhead & Indirect Cost of Processing | F22: =F15-F18-F20 -> 34096.41
A23: Including Profit
A25: (A) Details of Raw Materials of Imported / Undetermined Origin
A27: No | B27: Name of Materials | D27: Country of | E27: HS | F27: BE / invoice No | H27: Per Unit | I27: Quantity used | K27: Value of material
B28: Used | D28: Origin | E28: Code | F28: & Date | I28: in the Finished | K28: used in the
I29: Product | K29: Finished Product
B31: NOT APPLICABLE
I34: TOTAL
A36: (B) Details of Raw Materials of Indian Origin
A38: No | B38: Name of Materials | D38: Country of | E38: HS | F38: BE / invoice No | H38: Per Unit | I38: Quantity used | K38: Value of material
B39: Used | D39: Origin | E39: Code | F39: & Date | I39: in the Finished | K39: used in the
I40: Product | K40: Finished Product
A41: 1 | B41: POLYPROPYLENE | D41: INDIA | E41: 3902 | F41: 003/26-27 | H41: PCS | I41: 1 | K41: 168363
F42: DT 09.04.2026
I45: TOTAL | K45: =SUM(K41:L43) -> 168363
A47: Calculation of RVC/QVC/AIFTA Content as per the requirment of FTA / PTA / CEPA :
A49: Seal
A50: Stamp

Sheet OSWIN
A1: 265
A8: COST SHEET
A9: (For Certificate of Origin to be issued to Manufacturer Exporter or Merchant Exporter)
A11: Inv No | B11: =HP!B11:E11 -> JG/26-27/6002 | F11: Date | G11: =HP!G11:J11 -> 04.05.2026
A13: Name of the Finished Product | F13: PLASTIC (PP) EXTRUDED PIPES
A14: HS Code of the Product | F14: 3917.2200
A15: FOB Price / Ex-Work Price of Product | F15: 1231521.9
A16: 1. Value of imported / undetermined : Origin | F16: NIL
A17: raw material
A18: 2. Value of indigenous Raw Materials : | F18: =K41 -> 943795
A20: 3. Direct Cost of Processing | F20: =F18*10/100 -> 94379.5
A22: 4. Overhead & Indirect Cost of Processing | F22: =F15-F18-F20 -> 193347.38
A23: Including Profit
A25: (A) Details of Raw Materials of Imported / Undetermined Origin
A27: No | B27: Name of Materials | D27: Country of | E27: HS | F27: BE / invoice No | H27: Per Unit | I27: Quantity used | K27: Value of material
B28: Used | D28: Origin | E28: Code | F28: & Date | I28: in the Finished | K28: used in the
I29: Product | K29: Finished Product
B31: NOT APPLICABLE
I34: TOTAL
A36: (B) Details of Raw Materials of Indian Origin
A38: No | B38: Name of Materials | D38: Country of | E38: HS | F38: BE / invoice No | H38: Per Unit | I38: Quantity used | K38: Value of material
B39: Used | D39: Origin | E39: Code | F39: & Date | I39: in the Finished | K39: used in the
I40: Product | K40: Finished Product
A41: 1 | B41: POLYPROPYLENE | D41: INDIA | E41: 3902 | F41: DN-00259 | H41: PCS | I41: 1 | K41: 943795
F42: 04-05-2026
I45: TOTAL | K45: =SUM(K41:L43) -> 943795
A47: Calculation of RVC/QVC/AIFTA Content as per the requirment of FTA / PTA / CEPA :
A49: Seal
A50: Stamp

Sheet PUSHPAM
A8: COST SHEET
A9: (For Certificate of Origin to be issued to Manufacturer Exporter or Merchant Exporter)
A11: Inv No | B11: =HP!B11:E11 -> JG/26-27/6002 | F11: Date | G11: =HP!G11:J11 -> 04.05.2026
A13: Name of the Finished Product | F13: CORRUGATED BOXES
A14: HS Code of the Product | F14: 4819.1010
A15: FOB Price / Ex-Work Price of Product | F15: 80747.88
A16: 1. Value of imported / undetermined : Origin | F16: NIL
A17: raw material
A18: 2. Value of indigenous Raw Materials : | F18: =K45 -> 36776
A20: 3. Direct Cost of Processing | F20: =F18*40/100 -> 14710.4
A22: 4. Overhead & Indirect Cost of Processing | F22: =F15-F18-F20 -> 29261.48
A23: Including Profit
A25: (A) Details of Raw Materials of Imported / Undetermined Origin
A27: No | B27: Name of Materials | D27: Country of | E27: HS | F27: BE / invoice No | H27: Per Unit | I27: Quantity used | K27: Value of material
B28: Used | D28: Origin | E28: Code | F28: & Date | I28: in the Finished | K28: used in the
I29: Product | K29: Finished Product
B31: NOT APPLICABLE
I34: TOTAL
A36: (B) Details of Raw Materials of Indian Origin
A38: No | B38: Name of Materials | D38: Country of | E38: HS | F38: BE / invoice No | H38: Per Unit | I38: Quantity used | K38: Value of material
B39: Used | D39: Origin | E39: Code | F39: & Date | I39: in the Finished | K39: used in the
I40: Product | K40: Finished Product
A41: 1 | B41: PP SUNPAC SHEETS | D41: INDIA | E41: 3920 | F41: PC/0191/26-27 | H41: PCS | I41: 1 | K41: 36776
F42: 04-05-2026
I45: TOTAL | K45: =SUM(K41:L43) -> 36776
A47: Calculation of RVC/QVC/AIFTA Content as per the requirment of FTA / PTA / CEPA :
A49: Seal
A50: Stamp
