Workbook

Sheet Page1
A1: MERCHANT | B1: INVOICE
A2: JAIKVIN GLOBAL | F2: Invoice No. | G2: JG/26-27/6002 DT 04.05.2026 | K2: Exporter's Ref.
F3: Date: | K3: IEC AVIPS4808H
A4: Merchant Exporters | F4: Buyers Order No: | H4: 03320 DT 08.08.2025, 03455 DT.04.11.2025,
A5: A-101, Rajshree Royale, Navroji Lane, Ghatkopar (W), | H5: 03539 DT 08.01.2026, 03583 DT 12.02.2026,
A6: MUMBAI-400 086. Maharashtra (State Code : 27) | H6: 03605 DT. 25.02.2026, 03616 DT 04.03.2026,
A7: Tel: 9987122600 E-Mail: aalok.shah@jaikvinglobal.com | H7: 03658 DT. 02.04.2026
A8: On Account & Risks of: | F8: BL. NO. | G8: SFPM2605165498 DT. 19.05.2026
A9: Messrs Corecomp Pty Ltd.,
A10: T/A G.D.Watermark | F10: Shipped Per | G10: CAPE SYROS VOYAGE 092E
A11: 13, Tesla Link,
A12: Wangara WA 6065 (Australia) | F12: S/B No: | G12: 2945305 DT. 04.05.2026
A13: Invoice of: | B13: PP EXTRUDED PIPES, PP & NYLON MOULDED | F13: Country of Origin | I13: Country of Final Destination
B14: FITTINGS AND CORRUGATED BOXES | F14: INDIA | I14: AUSTRALIA
A16: Pre-Carraige by: | C16: Place of Receipt by Pre-Carraige | F16: Terms of Delivery: | H16: FOB MUMBAI
A18: Shipped per: | C18: Port of Loading: | F18: Terms of Payment: | H18: D.P.SIGHT DRAFT
A19: =G10 -> CAPE SYROS VOYAGE 092E | C19: NHAVA SHEVA-MUMBAI (INDIA)
A20: Port of Discharge: | C20: Port of destination | F20: Through: | H20: HDFC BANK LTD, GHATKOPAR (E) BRANCH
A21: FREMANTLE | C21: FREMANTLE | H21: GHATKOPAR (E), MUMBAI 400 077 (INDIA)
A22: Marks & Nos. | B22: No & Kinds of Pkgs Description of Goods | I22: Quantity | J22: Rate | K22: Amount
A23: GDW NOS : | B23: 421 PACKAGES (343 CARTONS & 78 HDP BUNDLES) CONTAINING | J23: FOB MUMBAI IN US$
A24: 2001 - 2421 | B24: PP EXTRUDED PIPES, PP & NYLON MOULDED FITTINGS & CORRUGATED BOXES
A25: 2421
B26: PP EXTRUDED PIPES : BOTH SIDE THREADED PIPES
B27: CODE | C27: SIZE (IN / MM) | D27: LEN (MM) | I27: PIECES | J27: PER PC
B28: PP1509 | C28: 15 | D28: 225 | I28: 6000 | J28: 0.07 | K28: =I28*J28 -> 420
B29: PP1518 | C29: 15 | D29: 457 | I29: 7200 | J29: 0.24 | K29: =I29*J29 -> 1728
B30: 90441400 | C30: 1/2" | D30: 450 | I30: 2600 | J30: 0.24 | K30: =I30*J30 -> 624
B31: PP1524 | C31: 15 | D31: 610 | I31: 2300 | J31: 0.3 | K31: =I31*J31 -> 690
B32: 90441600 | C32: 1/2" | D32: 600 | I32: 1600 | J32: 0.31 | K32: =I32*J32 -> 496
B33: PE1536 | C33: 15 | D33: 915 | I33: 1000 | J33: 0.41 | K33: =I33*J33 -> 410
B34: 90441800 | C34: 1/2" | D34: 900 | I34: 700 | J34: 0.44 | K34: =I34*J34 -> 308
B35: PE1548 | C35: 15 | D35: 1220 | I35: 50 | J35: 0.53 | K35: =I35*J35 -> 26.5
B36: PP2004 | C36: 20 | D36: 100 | I36: 500 | J36: 0.13 | K36: =I36*J36 -> 65
B37: 90447000 | C37: 3/4" | D37: 240 | I37: 4000 | J37: 0.22 | K37: =I37*J37 -> 880
B38: PE2018 | C38: 20 | D38: 457 | I38: 400 | J38: 0.35 | K38: =I38*J38 -> 140
B39: 90442400 | C39: 3/4" | D39: 450 | I39: 1600 | J39: 0.36 | K39: =I39*J39 -> 576
B40: PE2024 | C40: 20 | D40: 610 | I40: 1000 | J40: 0.45 | K40: =I40*J40 -> 450
B41: 90442700 | C41: 3/4" | D41: 750 | I41: 500 | J41: 0.56 | K41: =I41*J41 -> 280
B42: PP2508 | C42: 25 | D42: 200 | I42: 600 | J42: 0.24 | K42: =I42*J42 -> 144
B43: 90448000 | C43: 1" | D43: 270 | I43: 500 | J43: 0.35 | K43: =I43*J43 -> 175
B44: PE2515 | C44: 25 | D44: 375 | I44: 1000 | J44: 0.39 | K44: =I44*J44 -> 390
B45: PE2518 | C45: 25 | D45: 457 | I45: 2300 | J45: 0.45 | K45: =I45*J45 -> 1035
B46: 90443400 | C46: 1" | D46: 450 | I46: 800 | J46: 0.46 | K46: =I46*J46 -> 368
B47: PE2524 | C47: 25 | D47: 610 | I47: 400 | J47: 0.58 | K47: =I47*J47 -> 232
B48: 90443600 | C48: 1" | D48: 600 | I48: 500 | J48: 0.6 | K48: =I48*J48 -> 300
B49: 90443700 | C49: 1" | D49: 750 | I49: 500 | J49: 0.72 | K49: =I49*J49 -> 360
B50: 90443900 | C50: 1" | D50: 1800 | I50: 200 | J50: 1.66 | K50: =I50*J50 -> 332
B51: PE3206 | C51: 32 | D51: 150 | I51: 600 | J51: 0.28 | K51: =I51*J51 -> 168
B52: 90446200 | C52: 1-1/4" | D52: 150 | I52: 300 | J52: 0.29 | K52: =I52*J52 -> 87
B53: PE3218 | C53: 32 | D53: 450 | I53: 100 | J53: 0.6 | K53: =I53*J53 -> 60
B54: 90446400 | C54: 1-1/4" | D54: 450 | I54: 100 | J54: 0.63 | K54: =I54*J54 -> 63
B55: 90446600 | C55: 1-1/4" | D55: 600 | I55: 200 | J55: 0.8 | K55: =I55*J55 -> 160
B56: PE3230 | C56: 32 | D56: 750 | I56: 60 | J56: 0.93 | K56: =I56*J56 -> 55.8
B57: 90446700 | C57: 1-1/4" | D57: 900 | I57: 100 | J57: 1.15 | K57: =I57*J57 -> 115
B58: 90446800 | C58: 1-1/4" | D58: 1800 | I58: 50 | J58: 2.2 | K58: =I58*J58 -> 110
B59: 90447200 | C59: 1-1/2" | D59: 150 | I59: 300 | J59: 0.34 | K59: =I59*J59 -> 102
B60: PE4008 | C60: 40 | D60: 200 | I60: 150 | J60: 0.44 | K60: =I60*J60 -> 66
B61: PE4018 | C61: 40 | D61: 450 | I61: 100 | J61: 0.81 | K61: =I61*J61 -> 81
B62: 90447400 | C62: 1-1/2" | D62: 450 | I62: 200 | J62: 0.86 | K62: =I62*J62 -> 172
B63: PE5006 | C63: 50 | D63: 150 | I63: 150 | J63: 0.41 | K63: =I63*J63 -> 61.5
B64: 90448200 | C64: 2" | D64: 150 | I64: 150 | J64: 0.42 | K64: =I64*J64 -> 63
B65: 90448300 | C65: 2" | D65: 300 | I65: 75 | J65: 0.75 | K65: =I65*J65 -> 56.25
B66: PE5018 | C66: 50 | D66: 450 | I66: 100 | J66: 1.02 | K66: =I66*J66 -> 102
B67: 90448400 | C67: 2" | D67: 450 | I67: 100 | J67: 1.07 | K67: =I67*J67 -> 107
B68: 90448800 | C68: 2" | D68: 1200 | I68: 50 | J68: 2.69 | K68: =I68*J68 -> 134.5
B69: 90448820 | C69: 2" | D69: 1800 | I69: 60 | J69: 4.02 | K69: =I69*J69 -> 241.2
B70: PP EXTRUDED PIPES : M / F THREADED PIPES
B71: PMF2524 | C71: 25 | D71: 600 | I71: 100 | J71: 0.6 | K71: =I71*J71 -> 60
B72: 90445600 | C72: 1" | D72: 600 | I72: 500 | J72: 0.63 | K72: =I72*J72 -> 315
B73: 90445700 | C73: 1" | D73: 750 | I73: 200 | J73: 0.77 | K73: =I73*J73 -> 154
B74: PMF2536 | C74: 25 | D74: 900 | I74: 200 | J74: 0.86 | K74: =I74*J74 -> 172
B75: 90445800 | C75: 1" | D75: 900 | I75: 200 | J75: 0.89 | K75: =I75*J75 -> 178
B76: PP MOULDED FITTINGS
B77: CODE | C77: SIZE (IN / MM) | I77: PIECES | J77: PER 100 PCS
B78: PET1512 | C78: 15 | I78: 300 | J78: 14.4 | K78: =I78*J78/100 -> 43.2
B79: PP1501 / 5 | C79: 15 | I79: 4000 | J79: 13.8 | K79: =I79*J79/100 -> 552
B81: Total C/F Page :2 | G81: =SUM(G28:G80) -> 0 | K81: =SUM(K28:K80) -> 13908.95
A82: GSTIN : 27AVIPS4808H1Z8 w.e.f 20.01.2021 | H82: FOR JAIKVIN GLOBAL
A83: PAN No: AVIPS4808H
A84: Declaration:-
A85: We declare that this invoice shows the actual price of the goods described and that all particulars are true and correct.
A86: SUPPLY MEANT FOR EXPORT WITH PAYMENT OF INTEGRATED TAX
H87: PROPRIETOR

Sheet Page2
A1: =Page1!A1 -> MERCHANT | B1: =Page1!B1 -> INVOICE | K1: Page 2
A2: =Page1!A2 -> JAIKVIN GLOBAL | F2: =Page1!F2 -> Invoice No. | G2: =Page1!G2 -> JG/26-27/6002 DT 04.05.2026 | K2: =Page1!K2 -> Exporter's Ref.
F3: =Page1!F3 -> Date: | G3: =Page1!G3 -> 0 | K3: =Page1!K3 -> IEC AVIPS4808H
A4: =Page1!A4 -> Merchant Exporters | F4: Buyers Order No: | H4: 03320 DT 08.08.2025, 03455 DT.04.11.2025,
A5: =Page1!A5 -> A-101, Rajshree Royale, Navroji Lane, Ghatkopar (W), | H5: 03539 DT 08.01.2026, 03583 DT 12.02.2026,
A6: =Page1!A6 -> MUMBAI-400 086. Maharashtra (State Code : 27) | H6: 03605 DT. 25.02.2026, 03616 DT 04.03.2026,
A7: =Page1!A7 -> Tel: 9987122600 E-Mail: aalok.shah@jaikvinglobal.com | H7: 03658 DT. 02.04.2026
A8: =Page1!A8 -> On Account & Risks of: | C8: =Page1!C8 -> 0 | F8: =Page1!F8 -> BL. NO. | G8: =Page1!G8 -> SFPM2605165498 DT. 19.05.2026
A9: =Page1!A9 -> Messrs Corecomp Pty Ltd., | F9: =Page1!F9 -> 0 | G9: =Page1!G9 -> 0
A10: =Page1!A10 -> T/A G.D.Watermark | F10: =Page1!F10 -> Shipped Per | G10: =Page1!G10 -> CAPE SYROS VOYAGE 092E
A11: =Page1!A11 -> 13, Tesla Link, | F11: =Page1!F11 -> 0 | G11: =Page1!G11 -> 0
A12: =Page1!A12 -> Wangara WA 6065 (Australia) | F12: =Page1!F12 -> S/B No: | G12: =Page1!G12 -> 2945305 DT. 04.05.2026
A13: =Page1!A13 -> Invoice of: | B13: =Page1!B13 -> PP EXTRUDED PIPES, PP & NYLON MOULDED | F13: =Page1!F13 -> Country of Origin | I13: =Page1!I13 -> Country of Final Destination
A14: =Page1!A14 | B14: =Page1!B14 -> FITTINGS AND CORRUGATED BOXES | F14: =Page1!F14 -> INDIA | I14: =Page1!I14 -> AUSTRALIA
A15: =Page1!A15 | B15: =Page1!B15 -> 0
A16: =Page1!A16 -> Pre-Carraige by: | C16: =Page1!C16 -> Place of Receipt by Pre-Carraige | F16: Terms of Delivery: | H16: FOB MUMBAI
A17: =Page1!A17 | C17: =Page1!C17 -> 0
A18: =Page1!A18 -> Shipped per: | C18: =Page1!C18 -> Port of Loading: | F18: Terms of Payment: | H18: D.P.SIGHT DRAFT
A19: =Page1!A19 -> CAPE SYROS VOYAGE 092E | C19: =Page1!C19 -> NHAVA SHEVA-MUMBAI (INDIA)
A20: =Page1!A20 -> Port of Discharge: | C20: =Page1!C20 -> Port of destination | F20: Through: | H20: HDFC BANK LTD, GHATKOPAR (E) BRANCH
A21: =Page1!A21 -> FREMANTLE | C21: =Page1!C21 -> FREMANTLE | H21: GHATKOPAR (E), MUMBAI 400 077 (INDIA)
A22: Marks & Nos. | B22: No & Kinds of Pkgs Description of Goods | I22: Quantity | J22: Rate | K22: Amount
A23: =Page1!A23 -> GDW NOS : | B23: =Page1!B23 -> 421 PACKAGES (343 CARTONS & 78 HDP BUNDLES) CONTAINING | J23: =Page1!J23 -> FOB MUMBAI IN US$
A24: =Page1!A24 -> 2001 - 2421 | B24: =Page1!B24 -> PP EXTRUDED PIPES, PP & NYLON MOULDED FITTINGS & CORRUGATED BOXES
A25: =Page1!A25 -> 2421 | J25: =Page1!J25 -> 0 | K25: =Page1!K81 -> 13908.95
A26: =Page1!A26 -> 0 | B26: NYLON MOULDED FITTINGS
A27: =Page1!A27 -> 0 | B27: CODE | C27: SIZE (MM) | I27: PIECES | J27: PER 100 PCS
B28: GRC15 | C28: 15 | I28: 10000 | J28: 9.6 | K28: =I28*J28/100 -> 960
B29: GRC20 | C29: 20 | I29: 3000 | J29: 12 | K29: =I29*J29/100 -> 360
B30: GRC25 | C30: 25 | I30: 900 | J30: 15.6 | K30: =I30*J30/100 -> 140.4
A31: Container No. | B31: GRMFE25 | C31: 25 | I31: 1400 | J31: 33.6 | K31: =I31*J31/100 -> 470.4
A32: OOCU0793142 | B32: GRRS2015 | C32: 20*15 | I32: 1800 | J32: 21.6 | K32: =I32*J32/100 -> 388.8
B33: GRRS2520 | C33: 25*20 | I33: 1650 | J33: 24 | K33: =I33*J33/100 -> 396
B34: GRS25 | C34: 25 | I34: 500 | J34: 22.8 | K34: =I34*J34/100 -> 114
B35: GRT15 | C35: 15 | I35: 2160 | J35: 33.6 | K35: =I35*J35/100 -> 725.76
B36: GRT20 | C36: 20 | I36: 700 | J36: 40.8 | K36: =I36*J36/100 -> 285.6
B37: GRT25 | C37: 25 | I37: 1760 | J37: 50.4 | K37: =I37*J37/100 -> 887.04
B38: GRT32 | C38: 32 | I38: 1000 | J38: 91.2 | K38: =I38*J38/100 -> 912
B39: CORRUGATED BOXES
B40: CODE | C40: SIZE ( MM) | I40: PIECES | J40: PER PC
A41: Seal No. | B41: GD3 | C41: 570 X 368 X 178 | I41: 750 | J41: 0.85 | K41: =I41*J41 -> 637.5
A42: IND-0054079 | B42: GD4 | C42: 570 X 368 X 267 | I42: 277 | J42: 0.85 | K42: =I42*J42 -> 235.45
A50: Nett Wt.
A51: 6050.915
A52: KGS
A59: Gross Wt
A60: 6400
A61: KGS
A66: Freight
A67: Payable at
A68: Destination
A72: FOB VALUE
A73: =K74 -> 20421.9
B74: Total FOB Mumbai Value : | K74: =SUM(K25:K73) -> 20421.9
B75: US DOLLARS TWENTY THOUSAND FOUR HUNDRED TWENTY ONE AND CENTS NINETY ONLY
A77: GSTIN : 27AVIPS4808H1Z8 w.e.f 20.01.2021 | H77: FOR JAIKVIN GLOBAL
A78: PAN No: AVIPS4808H
A79: Declaration:-
A80: We declare that this invoice shows the actual price of the goods described and that all particulars are true and correct.
A81: SUPPLY MEANT FOR EXPORT WITH PAYMENT OF INTEGRATED TAX
H82: PROPRIETOR
